evogen/__init__.py
evogen/genetic_drift_fsim.py
evogen/plot.py
evogen/random_sampling.py
evogen/statistics.py
evogen/test_instllation.py
evogen-0.1.1.dist-info/LICENSE
evogen-0.1.1.dist-info/METADATA
evogen-0.1.1.dist-info/WHEEL
evogen-0.1.1.dist-info/top_level.txt
evogen-0.1.1.dist-info/RECORD
